txt2udp/__init__.py
txt2udp/cli.py
txt2udp/client.py
txt2udp/config.py
txt2udp/conn.py
txt2udp/datagram.py
txt2udp/main.py
txt2udp/messages.py
txt2udp/server.py
txt2udp/plugins/__init__.py
txt2udp/plugins/mitm.py
txt2udp/plugins/stdio.py
txt2udp-0.1.4.dist-info/LICENSE
txt2udp-0.1.4.dist-info/METADATA
txt2udp-0.1.4.dist-info/WHEEL
txt2udp-0.1.4.dist-info/entry_points.txt
txt2udp-0.1.4.dist-info/top_level.txt
txt2udp-0.1.4.dist-info/RECORD
