Metadata-Version: 2.1
Name: txt2udp
Version: 0.1.4
Summary: A simple tool for forwarding UDP datagrams through a text-only protocol/interface.
Home-page: https://github.com/mirrorange/TXT2UDP
Author: Orange
Author-email: orange@icedeer.net
License: Apache-2.0
License-File: LICENSE
Requires-Dist: pydantic
Requires-Dist: pydantic-settings
Requires-Dist: loguru
Provides-Extra: all
Requires-Dist: mitmproxy ; extra == 'all'
Requires-Dist: typer ; extra == 'all'
Provides-Extra: cli
Requires-Dist: typer ; extra == 'cli'
Provides-Extra: mitm
Requires-Dist: mitmproxy ; extra == 'mitm'
